sphinx_highlights/__init__.py
sphinx_highlights/_eval_type.py
sphinx_highlights/py.typed
sphinx_highlights-0.6.0.dist-info/LICENSE
sphinx_highlights-0.6.0.dist-info/METADATA
sphinx_highlights-0.6.0.dist-info/WHEEL
sphinx_highlights-0.6.0.dist-info/entry_points.txt
sphinx_highlights-0.6.0.dist-info/RECORD
