Metadata-Version: 2.1
Name: sphinx-highlights
Version: 0.6.0
Summary: Sphinx extension to display a selection of highlights from a Python library.
Author-email: Dominic Davis-Foster <dominic@davis-foster.co.uk>
License: MIT
Keywords: documentation,sphinx,sphinx-extension
Home-page: https://github.com/sphinx-toolbox/sphinx-highlights
Project-URL: Issue Tracker, https://github.com/sphinx-toolbox/sphinx-highlights/issues
Project-URL: Source Code, https://github.com/sphinx-toolbox/sphinx-highlights
Project-URL: Documentation, https://sphinx-highlights.readthedocs.io/en/latest
Platform: Windows
Platform: macOS
Platform: Linux
Classifier: Development Status :: 4 - Beta
Classifier: Framework :: Sphinx :: Extension
Classifier: Intended Audience :: Developers
Classifier: License :: OSI Approved :: MIT License
Classifier: Operating System :: OS Independent
Classifier: Programming Language :: Python
Classifier: Programming Language :: Python :: 3 :: Only
Classifier: Programming Language :: Python :: 3.7
Classifier: Programming Language :: Python :: 3.8
Classifier: Programming Language :: Python :: 3.9
Classifier: Programming Language :: Python :: 3.10
Classifier: Programming Language :: Python :: 3.11
Classifier: Programming Language :: Python :: 3.12
Classifier: Programming Language :: Python :: Implementation :: CPython
Classifier: Programming Language :: Python :: Implementation :: PyPy
Classifier: Topic :: Documentation
Classifier: Topic :: Documentation :: Sphinx
Classifier: Topic :: Software Development :: Documentation
Classifier: Topic :: Utilities
Classifier: Typing :: Typed
Requires-Python: >=3.7
Requires-Dist: default-values>=0.5.0
Requires-Dist: dict2css>=0.2.3
Requires-Dist: docutils>=0.16
Requires-Dist: domdf-python-tools>=2.9.0
Requires-Dist: sphinx<5,>=3.2.0
Requires-Dist: sphinx-panels>=0.5.1
Requires-Dist: sphinx-toolbox>=2.13.0
